{
	"recordList": [{
		"id": 1,
		"picname": "螺旋木勺",
		"pictype": "v",
		"picurl": "wood/wood001.jpg"
	}, {
		"id": 2,
		"picname": "螺旋中轴",
		"pictype": "v",
		"picurl": "wood/wood002.jpg"
	}, {
		"id": 3,
		"picname": "床头柜",
		"pictype": "v",
		"picurl": "wood/wood003.jpg"
	}, {
		"id": 4,
		"picname": "欧式茶几",
		"pictype": "v",
		"picurl": "wood/wood004.jpg"
	}, {
		"id": 5,
		"picname": "工作台",
		"pictype": "h",
		"picurl": "wood/wood005.jpg"
	}, {
		"id": 6,
		"picname": "工作台",
		"pictype": "v",
		"picurl": "wood/wood006.jpg"
	}, {
		"id": 7,
		"picname": "迷你榔头",
		"pictype": "v",
		"picurl": "wood/wood007.jpg"
	}, {
		"id": 8,
		"picname": "明式圈椅",
		"pictype": "v",
		"picurl": "wood/wood008.jpg"
	}, {
		"id": 9,
		"picname": "明式圈椅",
		"pictype": "h",
		"picurl": "wood/wood009.jpg"
	}, {
		"id": 10,
		"picname": "实木床设计图",
		"pictype": "h",
		"picurl": "wood/wood010.jpg"
	}, {
		"id": 11,
		"picname": "厨房道具",
		"pictype": "v",
		"picurl": "wood/wood011.jpg"
	}, {
		"id": 12,
		"picname": "茶几",
		"pictype": "h",
		"picurl": "wood/wood012.jpg"
	}, {
		"id": 13,
		"picname": "杂物盒",
		"pictype": "v",
		"picurl": "wood/wood013.jpg"
	}, {
		"id": 14,
		"picname": "工具盒",
		"pictype": "h",
		"picurl": "wood/wood014.jpg"
	}, {
		"id": 15,
		"picname": "月牙弧板凳",
		"pictype": "v",
		"picurl": "wood/wood015.jpg"
	}, {
		"id": 16,
		"picname": "书架",
		"pictype": "v",
		"picurl": "wood/wood016.jpg"
	}, {
		"id": 17,
		"picname": "榫头",
		"pictype": "v",
		"picurl": "wood/wood017.jpg"
	}, {
		"id": 18,
		"picname": "窗边柜",
		"pictype": "v",
		"picurl": "wood/wood018.jpg"
	}, {
		"id": 19,
		"picname": "杂物架",
		"pictype": "v",
		"picurl": "wood/wood019.jpg"
	}, {
		"id": 20,
		"picname": "托盘",
		"pictype": "h",
		"picurl": "wood/wood020.jpg"
	}, {
		"id": 21,
		"picname": "多功能椅",
		"pictype": "v",
		"picurl": "wood/wood021.jpg"
	}, {
		"id": 22,
		"picname": "办公窗",
		"pictype": "h",
		"picurl": "wood/wood022.jpg"
	}, {
		"id": 23,
		"picname": "精油盒",
		"pictype": "h",
		"picurl": "wood/wood023.jpg"
	}, {
		"id": 24,
		"picname": "刀架",
		"pictype": "h",
		"picurl": "wood/wood024.jpg"
	}, {
		"id": 25,
		"picname": "鸟笼",
		"pictype": "v",
		"picurl": "wood/wood025.jpg"
	}, {
		"id": 26,
		"picname": "木门",
		"pictype": "v",
		"picurl": "wood/wood026.jpg"
	}, {
		"id": 27,
		"picname": "台架",
		"pictype": "v",
		"picurl": "wood/wood027.jpg"
	}, {
		"id": 28,
		"picname": "靠背椅",
		"pictype": "v",
		"picurl": "wood/wood028.jpg"
	}, {
		"id": 29,
		"picname": "靠背椅制作",
		"pictype": "v",
		"picurl": "wood/wood029.jpg"
	}, {
		"id": 30,
		"picname": "陀螺制作",
		"pictype": "v",
		"picurl": "wood/wood030.jpg"
	}, {
		"id": 31,
		"picname": "陀螺",
		"pictype": "v",
		"picurl": "wood/wood031.jpg"
	}, {
		"id": 32,
		"picname": "花盆",
		"pictype": "v",
		"picurl": "wood/wood032.jpg"
	}, {
		"id": 33,
		"picname": "杯子",
		"pictype": "v",
		"picurl": "wood/wood033.jpg"
	}, {
		"id": 34,
		"picname": "迷你棒球棍制作",
		"pictype": "v",
		"picurl": "wood/wood034.jpg"
	}, {
		"id": 35,
		"picname": "迷你棒球棍",
		"pictype": "v",
		"picurl": "wood/wood035.jpg"
	}, {
		"id": 36,
		"picname": "木碗制作",
		"pictype": "v",
		"picurl": "wood/wood036.jpg"
	}, {
		"id": 37,
		"picname": "木碗",
		"pictype": "v",
		"picurl": "wood/wood037.jpg"
	}]
}